MANIFEST.in
README.md
setup.py
pyVows.egg-info/PKG-INFO
pyVows.egg-info/SOURCES.txt
pyVows.egg-info/dependency_links.txt
pyVows.egg-info/entry_points.txt
pyVows.egg-info/requires.txt
pyVows.egg-info/top_level.txt
pyvows/__init__.py
pyvows/__main__.py
pyvows/async_topic.py
pyvows/cli.py
pyvows/color.py
pyvows/commands.py
pyvows/core.py
pyvows/decorators.py
pyvows/errors.py
pyvows/result.py
pyvows/utils.py
pyvows/version.py
pyvows/reporting/__init__.py
pyvows/reporting/common.py
pyvows/reporting/coverage.py
pyvows/reporting/profile.py
pyvows/reporting/test.py
pyvows/reporting/xunit.py
pyvows/runner/__init__.py
pyvows/runner/abc.py
pyvows/runner/executionplan.py
pyvows/runner/gevent.py
pyvows/runner/sequential.py
pyvows/runner/utils.py
tests/__init__.py
tests/async_vows.py
tests/captured_output_vows.py
tests/cli_vows.py
tests/context_inheritance_vows.py
tests/division_vows.py
tests/docstring_vows.py
tests/errors_in_topic_vows.py
tests/filter_vows_to_run_vows.py
tests/fruits_vows.py
tests/generator_vows.py
tests/multiple_topic_vows.py
tests/no_subcontext_extension_vows.py
tests/prune_execution_vows.py
tests/setup_teardown_vows.py
tests/skipping_vows.py
tests/utils_vows.py
tests/version_vows.py
tests/assertions/__init__.py
tests/assertions/assertion_vows.py
tests/assertions/emptiness_vows.py
tests/assertions/equality_vows.py
tests/assertions/inclusion_vows.py
tests/assertions/length_vows.py
tests/assertions/like_vows.py
tests/assertions/types/__init__.py
tests/assertions/types/boolean_vows.py
tests/assertions/types/classes_vows.py
tests/assertions/types/errors_vows.py
tests/assertions/types/file_vows.py
tests/assertions/types/function_vows.py
tests/assertions/types/nullable_vows.py
tests/assertions/types/numeric_vows.py
tests/assertions/types/regexp_vows.py
tests/bugs/64_vows.py
tests/bugs/__init__.py
tests/reporting/__init__.py
tests/reporting/error_reporting_vows.py
tests/reporting/reporting_vows.py
tests/reporting/xunit_reporter_vows.py