Metadata-Version: 2.1
Name: pyVows
Version: 3.0.0
Summary: pyVows is a BDD test engine based on Vows.js <http://vowsjs.org>.
Home-page: http://pyvows.org
Author: Bernardo Heynemann
Author-email: heynemann@gmail.com
Maintainer: Zearin
License: MIT
Keywords: test testing vows tdd bdd development coverage profile profiling
Platform: UNKNOWN
Classifier: Development Status :: 4 - Beta
Classifier: Intended Audience :: Developers
Classifier: License :: OSI Approved :: MIT License
Classifier: Natural Language :: English
Classifier: Operating System :: MacOS
Classifier: Operating System :: POSIX
Classifier: Operating System :: Unix
Classifier: Operating System :: OS Independent
Classifier: Programming Language :: Python :: 2.6
Classifier: Programming Language :: Python :: 2.7
Classifier: Topic :: Software Development :: Testing
Provides-Extra: tests
